flask_confluent_kafka/__init__.py
flask_confluent_kafka/core.py
flask_confluent_kafka-0.1.1.dist-info/METADATA
flask_confluent_kafka-0.1.1.dist-info/WHEEL
flask_confluent_kafka-0.1.1.dist-info/entry_points.txt
flask_confluent_kafka-0.1.1.dist-info/RECORD
